yuanqiserver/__init__.py
yuanqiserver/__main__.py
yuanqiserver/exceptions.py
yuanqiserver/main.py
yuanqiserver-1.1.7.dist-info/METADATA
yuanqiserver-1.1.7.dist-info/WHEEL
yuanqiserver-1.1.7.dist-info/entry_points.txt
yuanqiserver-1.1.7.dist-info/top_level.txt
yuanqiserver-1.1.7.dist-info/RECORD
